accbpg/D_opt_alg.py
accbpg/__init__.py
accbpg/algorithms.py
accbpg/applications.py
accbpg/ex_LR_L2L1Linf.py
accbpg/functions.py
accbpg/plotfigs.py
accbpg/trianglescaling.py
accbpg/utils.py
accbpg-0.2.dist-info/LICENSE
accbpg-0.2.dist-info/METADATA
accbpg-0.2.dist-info/WHEEL
accbpg-0.2.dist-info/top_level.txt
accbpg-0.2.dist-info/RECORD
