Metadata-Version: 2.1
Name: accbpg
Version: 0.2
Summary: Accelerated Bregman proximal gradient (ABPG) methods
Home-page: https://github.com/Microsoft/accbpg
Author: Lin Xiao
Author-email: lin.xiao@gmail.com
License: MIT
Platform: UNKNOWN
Requires-Dist: numpy
Requires-Dist: scipy
